fmops/__init__.py
fmops-0.0.1.dist-info/LICENSE
fmops-0.0.1.dist-info/METADATA
fmops-0.0.1.dist-info/WHEEL
fmops-0.0.1.dist-info/RECORD
