Metadata-Version: 2.1
Name: fmops
Version: 0.0.1
Summary: FMOps Python SDK
License: Apache 2.0
Author: Feynman Liang
Author-email: feynman.liang@gmail.com
Requires-Python: >=3.9,<4.0
Classifier: License :: Other/Proprietary License
Classifier: Programming Language :: Python :: 3
Classifier: Programming Language :: Python :: 3.9
Classifier: Programming Language :: Python :: 3.10
Classifier: Programming Language :: Python :: 3.11
